django-influxdb/__init__.py
django-influxdb/base.py
django-influxdb/features.py
django_influxdb-0.1.4.dist-info/DESCRIPTION.rst
django_influxdb-0.1.4.dist-info/METADATA
django_influxdb-0.1.4.dist-info/RECORD
django_influxdb-0.1.4.dist-info/WHEEL
django_influxdb-0.1.4.dist-info/metadata.json
django_influxdb-0.1.4.dist-info/top_level.txt
influddbAPI2/__init__.py
influddbAPI2/dbapi2.py
influxdb/__init__.py
influxdb/base.py
influxdb/features.py
