Metadata-Version: 2.0
Name: django-influxdb
Version: 0.1.4
Summary: InfluxDB Django backend
Home-page: https://github.com/oritec/django-influxdb
Author: Oritec SpA
Author-email: servicios@oritec.cl
License: UNKNOWN
Keywords: django influxdb
Platform: UNKNOWN
Classifier: Development Status :: 3 - Alpha
Classifier: Intended Audience :: Developers
Classifier: Topic :: Software Development :: Build Tools
Classifier: License :: OSI Approved :: MIT License
Classifier: Programming Language :: Python :: 2
Classifier: Programming Language :: Python :: 2.7
Classifier: Programming Language :: Python :: 3
Classifier: Programming Language :: Python :: 3.4
Classifier: Programming Language :: Python :: 3.5
Classifier: Programming Language :: Python :: 3.6
Provides-Extra: test
Provides-Extra: dev
Requires-Dist: influxdb
Provides-Extra: dev
Requires-Dist: influxdb; extra == 'dev'
Provides-Extra: test
Requires-Dist: influxdb; extra == 'test'
